{".class": "MypyFile", "_fullname": "ninja.schema", "is_partial_stub_package": false, "is_stub": false, "names": {".class": "SymbolTable", "Any": {".class": "SymbolTableNode", "cross_ref": "typing.Any", "kind": "Gdef", "module_public": false}, "BaseModel": {".class": "SymbolTableNode", "cross_ref": "pydantic.main.BaseModel", "kind": "Gdef"}, "Callable": {".class": "SymbolTableNode", "cross_ref": "typing.Callable", "kind": "Gdef", "module_public": false}, "Dict": {".class": "SymbolTableNode", "cross_ref": "typing.Dict", "kind": "Gdef", "module_public": false}, "DjangoGetter": {".class": "SymbolTableNode", "kind": "Gdef", "node": {".class": "TypeInfo", "_promote": null, "abstract_attributes": [], "bases": ["pydantic.utils.GetterDict"], "declared_metaclass": null, "defn": {".class": "ClassDef", "fullname": "ninja.schema.DjangoGetter", "name": "DjangoGetter", "type_vars": []}, "flags": [], "fullname": "ninja.schema.DjangoGetter", "metaclass_type": null, "metadata": {}, "module_name": "ninja.schema", "mro": ["ninja.schema.DjangoGetter", "pydantic.utils.GetterDict", "pydantic.utils.Representation", "builtins.object"], "names": {".class": "SymbolTable", "__getitem__": {".class": "SymbolTableNode", "kind": "Mdef", "node": {".class": "FuncDef", "arg_kinds": [0, 0], "arg_names": ["self", "key"], "flags": [], "fullname": "ninja.schema.DjangoGetter.__getitem__", "name": "__getitem__", "type": {".class": "CallableType", "arg_kinds": [0, 0], "arg_names": [null, null], "arg_types": ["ninja.schema.DjangoGetter", "builtins.str"], "bound_args": [], "def_extras": {"first_arg": "self"}, "fallback": "builtins.function", "implicit": false, "is_ellipsis_args": false, "name": "__getitem__ of DjangoGetter", "ret_type": {".class": "AnyType", "missing_import_name": null, "source_any": null, "type_of_any": 2}, "variables": []}}}, "__init__": {".class": "SymbolTableNode", "kind": "Mdef", "node": {".class": "FuncDef", "arg_kinds": [0, 0, 0], "arg_names": ["self", "obj", "schema_cls"], "flags": [], "fullname": "ninja.schema.DjangoGetter.__init__", "name": "__init__", "type": {".class": "CallableType", "arg_kinds": [0, 0, 0], "arg_names": ["self", "obj", "schema_cls"], "arg_types": ["ninja.schema.DjangoGetter", {".class": "AnyType", "missing_import_name": null, "source_any": null, "type_of_any": 2}, {".class": "TypeType", "item": "ninja.schema.Schema"}], "bound_args": [], "def_extras": {"first_arg": "self"}, "fallback": "builtins.function", "implicit": false, "is_ellipsis_args": false, "name": "__init__ of DjangoGetter", "ret_type": {".class": "NoneType"}, "variables": []}}}, "__slots__": {".class": "SymbolTableNode", "kind": "Mdef", "node": {".class": "Var", "flags": ["is_initialized_in_class"], "fullname": "ninja.schema.DjangoGetter.__slots__", "name": "__slots__", "type": {".class": "TupleType", "implicit": false, "items": ["builtins.str", "builtins.str"], "partial_fallback": {".class": "Instance", "args": [{".class": "AnyType", "missing_import_name": null, "source_any": null, "type_of_any": 6}], "type_ref": "builtins.tuple"}}}}, "_convert_result": {".class": "SymbolTableNode", "kind": "Mdef", "node": {".class": "FuncDef", "arg_kinds": [0, 0], "arg_names": ["self", "result"], "flags": [], "fullname": "ninja.schema.DjangoGetter._convert_result", "name": "_convert_result", "type": {".class": "CallableType", "arg_kinds": [0, 0], "arg_names": ["self", "result"], "arg_types": ["ninja.schema.DjangoGetter", {".class": "AnyType", "missing_import_name": null, "source_any": null, "type_of_any": 2}], "bound_args": [], "def_extras": {"first_arg": "self"}, "fallback": "builtins.function", "implicit": false, "is_ellipsis_args": false, "name": "_convert_result of DjangoGetter", "ret_type": {".class": "AnyType", "missing_import_name": null, "source_any": null, "type_of_any": 2}, "variables": []}}}, "_schema_cls": {".class": "SymbolTableNode", "implicit": true, "kind": "Mdef", "node": {".class": "Var", "flags": [], "fullname": "ninja.schema.DjangoGetter._schema_cls", "name": "_schema_cls", "type": {".class": "TypeType", "item": "ninja.schema.Schema"}}}, "get": {".class": "SymbolTableNode", "kind": "Mdef", "node": {".class": "FuncDef", "arg_kinds": [0, 0, 1], "arg_names": ["self", "key", "default"], "flags": [], "fullname": "ninja.schema.DjangoGetter.get", "name": "get", "type": {".class": "CallableType", "arg_kinds": [0, 0, 1], "arg_names": ["self", "key", "default"], "arg_types": ["ninja.schema.DjangoGetter", {".class": "AnyType", "missing_import_name": null, "source_any": null, "type_of_any": 2}, {".class": "UnionType", "items": [{".class": "AnyType", "missing_import_name": null, "source_any": null, "type_of_any": 2}, {".class": "NoneType"}]}], "bound_args": [], "def_extras": {"first_arg": "self"}, "fallback": "builtins.function", "implicit": false, "is_ellipsis_args": false, "name": "get of DjangoGetter", "ret_type": {".class": "AnyType", "missing_import_name": null, "source_any": null, "type_of_any": 2}, "variables": []}}}}, "tuple_type": null, "type_vars": [], "typeddict_type": null}}, "Field": {".class": "SymbolTableNode", "cross_ref": "pydantic.fields.Field", "kind": "Gdef"}, "FieldFile": {".class": "SymbolTableNode", "kind": "Gdef", "module_public": false, "node": {".class": "Var", "flags": ["is_suppressed_import", "is_ready"], "fullname": "ninja.schema.FieldFile", "name": "FieldFile", "type": {".class": "AnyType", "missing_import_name": "ninja.schema.FieldFile", "source_any": null, "type_of_any": 3}}}, "GetterDict": {".class": "SymbolTableNode", "cross_ref": "pydantic.utils.GetterDict", "kind": "Gdef", "module_public": false}, "Manager": {".class": "SymbolTableNode", "kind": "Gdef", "module_public": false, "node": {".class": "Var", "flags": ["is_suppressed_import", "is_ready"], "fullname": "ninja.schema.Manager", "name": "Manager", "type": {".class": "AnyType", "missing_import_name": "ninja.schema.Manager", "source_any": null, "type_of_any": 3}}}, "ModelMetaclass": {".class": "SymbolTableNode", "cross_ref": "pydantic.main.ModelMetaclass", "kind": "Gdef", "module_public": false}, "PartialSchema@113": {".class": "SymbolTableNode", "kind": "Gdef", "node": {".class": "TypeInfo", "_promote": null, "abstract_attributes": [], "bases": ["ninja.schema.Schema"], "declared_metaclass": null, "defn": {".class": "ClassDef", "fullname": "ninja.schema.PartialSchema@113", "name": "PartialSchema", "type_vars": []}, "flags": [], "fullname": "ninja.schema.PartialSchema@113", "metaclass_type": "ninja.schema.ResolverMetaclass", "metadata": {}, "module_name": "ninja.schema", "mro": ["ninja.schema.PartialSchema@113", "ninja.schema.Schema", "pydantic.main.BaseModel", "pydantic.utils.Representation", "builtins.object"], "names": {".class": "SymbolTable", "__getattr__": {".class": "SymbolTableNode", "kind": "Mdef", "node": {".class": "FuncDef", "arg_kinds": [0, 0], "arg_names": ["self", "key"], "flags": [], "fullname": "ninja.schema.PartialSchema@113.__getattr__", "name": "__getattr__", "type": {".class": "CallableType", "arg_kinds": [0, 0], "arg_names": [null, null], "arg_types": ["ninja.schema.PartialSchema@113", "builtins.str"], "bound_args": [], "def_extras": {"first_arg": "self"}, "fallback": "builtins.function", "implicit": false, "is_ellipsis_args": false, "name": "__getattr__ of PartialSchema", "ret_type": {".class": "AnyType", "missing_import_name": null, "source_any": null, "type_of_any": 2}, "variables": []}}}}, "tuple_type": null, "type_vars": [], "typeddict_type": null}}, "QuerySet": {".class": "SymbolTableNode", "kind": "Gdef", "module_public": false, "node": {".class": "Var", "flags": ["is_suppressed_import", "is_ready"], "fullname": "ninja.schema.QuerySet", "name": "QuerySet", "type": {".class": "AnyType", "missing_import_name": "ninja.schema.QuerySet", "source_any": null, "type_of_any": 3}}}, "Resolver": {".class": "SymbolTableNode", "kind": "Gdef", "module_public": false, "node": {".class": "TypeInfo", "_promote": null, "abstract_attributes": [], "bases": ["builtins.object"], "declared_metaclass": null, "defn": {".class": "ClassDef", "fullname": "ninja.schema.Resolver", "name": "Resolver", "type_vars": []}, "flags": [], "fullname": "ninja.schema.Resolver", "metaclass_type": null, "metadata": {}, "module_name": "ninja.schema", "mro": ["ninja.schema.Resolver", "builtins.object"], "names": {".class": "SymbolTable", "__call__": {".class": "SymbolTableNode", "kind": "Mdef", "node": {".class": "FuncDef", "arg_kinds": [0, 0], "arg_names": ["self", "getter"], "flags": [], "fullname": "ninja.schema.Resolver.__call__", "name": "__call__", "type": {".class": "CallableType", "arg_kinds": [0, 0], "arg_names": ["self", "getter"], "arg_types": ["ninja.schema.Resolver", "ninja.schema.DjangoGetter"], "bound_args": [], "def_extras": {"first_arg": "self"}, "fallback": "builtins.function", "implicit": false, "is_ellipsis_args": false, "name": "__call__ of Resolver", "ret_type": {".class": "AnyType", "missing_import_name": null, "source_any": null, "type_of_any": 2}, "variables": []}}}, "__init__": {".class": "SymbolTableNode", "kind": "Mdef", "node": {".class": "FuncDef", "arg_kinds": [0, 0], "arg_names": ["self", "func"], "flags": [], "fullname": "ninja.schema.Resolver.__init__", "name": "__init__", "type": {".class": "CallableType", "arg_kinds": [0, 0], "arg_names": ["self", "func"], "arg_types": ["ninja.schema.Resolver", {".class": "UnionType", "items": [{".class": "CallableType", "arg_kinds": [2, 4], "arg_names": [null, null], "arg_types": [{".class": "AnyType", "missing_import_name": null, "source_any": null, "type_of_any": 4}, {".class": "AnyType", "missing_import_name": null, "source_any": null, "type_of_any": 4}], "bound_args": [], "def_extras": {}, "fallback": "builtins.function", "implicit": false, "is_ellipsis_args": true, "name": null, "ret_type": {".class": "AnyType", "missing_import_name": null, "source_any": null, "type_of_any": 4}, "variables": []}, "builtins.staticmethod"]}], "bound_args": [], "def_extras": {"first_arg": "self"}, "fallback": "builtins.function", "implicit": false, "is_ellipsis_args": false, "name": "__init__ of Resolver", "ret_type": {".class": "NoneType"}, "variables": []}}}, "__slots__": {".class": "SymbolTableNode", "kind": "Mdef", "node": {".class": "Var", "flags": ["is_initialized_in_class"], "fullname": "ninja.schema.Resolver.__slots__", "name": "__slots__", "type": {".class": "TupleType", "implicit": false, "items": ["builtins.str", "builtins.str"], "partial_fallback": {".class": "Instance", "args": [{".class": "AnyType", "missing_import_name": null, "source_any": null, "type_of_any": 6}], "type_ref": "builtins.tuple"}}}}, "_fake_instance": {".class": "SymbolTableNode", "kind": "Mdef", "node": {".class": "FuncDef", "arg_kinds": [0, 0], "arg_names": ["self", "getter"], "flags": [], "fullname": "ninja.schema.Resolver._fake_instance", "name": "_fake_instance", "type": {".class": "CallableType", "arg_kinds": [0, 0], "arg_names": ["self", "getter"], "arg_types": ["ninja.schema.Resolver", "ninja.schema.DjangoGetter"], "bound_args": [], "def_extras": {"first_arg": "self"}, "fallback": "builtins.function", "implicit": false, "is_ellipsis_args": false, "name": "_fake_instance of Resolver", "ret_type": "ninja.schema.Schema", "variables": []}}}, "_func": {".class": "SymbolTableNode", "kind": "Mdef", "node": {".class": "Var", "flags": ["is_initialized_in_class", "is_ready"], "fullname": "ninja.schema.Resolver._func", "name": "_func", "type": {".class": "AnyType", "missing_import_name": null, "source_any": null, "type_of_any": 2}}}, "_static": {".class": "SymbolTableNode", "kind": "Mdef", "node": {".class": "Var", "flags": ["is_initialized_in_class", "is_ready"], "fullname": "ninja.schema.Resolver._static", "name": "_static", "type": "builtins.bool"}}}, "tuple_type": null, "type_vars": [], "typeddict_type": null}}, "ResolverMetaclass": {".class": "SymbolTableNode", "kind": "Gdef", "module_public": false, "node": {".class": "TypeInfo", "_promote": null, "abstract_attributes": [], "bases": ["pydantic.main.ModelMetaclass"], "declared_metaclass": null, "defn": {".class": "ClassDef", "fullname": "ninja.schema.ResolverMetaclass", "name": "ResolverMetaclass", "type_vars": []}, "flags": [], "fullname": "ninja.schema.ResolverMetaclass", "metaclass_type": null, "metadata": {}, "module_name": "ninja.schema", "mro": ["ninja.schema.ResolverMetaclass", "pydantic.main.ModelMetaclass", "abc.ABCMeta", "builtins.type", "builtins.object"], "names": {".class": "SymbolTable", "__new__": {".class": "SymbolTableNode", "kind": "Mdef", "node": {".class": "Decorator", "func": {".class": "FuncDef", "arg_kinds": [0, 0, 0, 0, 4], "arg_names": ["cls", "name", "bases", "namespace", "kwargs"], "flags": ["is_decorated"], "fullname": "ninja.schema.ResolverMetaclass.__new__", "name": "__new__", "type": null}, "is_overload": false, "var": {".class": "Var", "flags": ["is_initialized_in_class", "is_ready"], "fullname": null, "name": "__new__", "type": {".class": "AnyType", "missing_import_name": null, "source_any": null, "type_of_any": 6}}}}, "_ninja_resolvers": {".class": "SymbolTableNode", "kind": "Mdef", "node": {".class": "Var", "flags": ["is_initialized_in_class", "is_ready"], "fullname": "ninja.schema.ResolverMetaclass._ninja_resolvers", "name": "_ninja_resolvers", "type": {".class": "Instance", "args": ["builtins.str", "ninja.schema.Resolver"], "type_ref": "builtins.dict"}}}}, "tuple_type": null, "type_vars": [], "typeddict_type": null}}, "S": {".class": "SymbolTableNode", "kind": "Gdef", "module_public": false, "node": {".class": "TypeVarExpr", "fullname": "ninja.schema.S", "name": "S", "upper_bound": "ninja.schema.Schema", "values": [], "variance": 0}}, "Schema": {".class": "SymbolTableNode", "kind": "Gdef", "node": {".class": "TypeInfo", "_promote": null, "abstract_attributes": [], "bases": ["pydantic.main.BaseModel"], "declared_metaclass": "ninja.schema.ResolverMetaclass", "defn": {".class": "ClassDef", "fullname": "ninja.schema.Schema", "name": "Schema", "type_vars": []}, "flags": [], "fullname": "ninja.schema.Schema", "metaclass_type": "ninja.schema.ResolverMetaclass", "metadata": {}, "module_name": "ninja.schema", "mro": ["ninja.schema.Schema", "pydantic.main.BaseModel", "pydantic.utils.Representation", "builtins.object"], "names": {".class": "SymbolTable", "Config": {".class": "SymbolTableNode", "kind": "Mdef", "node": {".class": "TypeInfo", "_promote": null, "abstract_attributes": [], "bases": ["builtins.object"], "declared_metaclass": null, "defn": {".class": "ClassDef", "fullname": "ninja.schema.Schema.Config", "name": "Config", "type_vars": []}, "flags": [], "fullname": "ninja.schema.Schema.Config", "metaclass_type": null, "metadata": {}, "module_name": "ninja.schema", "mro": ["ninja.schema.Schema.Config", "builtins.object"], "names": {".class": "SymbolTable", "getter_dict": {".class": "SymbolTableNode", "kind": "Mdef", "node": {".class": "Var", "flags": ["is_initialized_in_class"], "fullname": "ninja.schema.Schema.Config.getter_dict", "name": "getter_dict", "type": {".class": "CallableType", "arg_kinds": [0, 0], "arg_names": ["obj", "schema_cls"], "arg_types": [{".class": "AnyType", "missing_import_name": null, "source_any": null, "type_of_any": 2}, {".class": "TypeType", "item": "ninja.schema.Schema"}], "bound_args": ["ninja.schema.DjangoGetter"], "def_extras": {"first_arg": "self"}, "fallback": "builtins.type", "implicit": false, "is_ellipsis_args": false, "name": null, "ret_type": "ninja.schema.DjangoGetter", "variables": []}}}, "orm_mode": {".class": "SymbolTableNode", "kind": "Mdef", "node": {".class": "Var", "flags": ["is_initialized_in_class"], "fullname": "ninja.schema.Schema.Config.orm_mode", "name": "orm_mode", "type": "builtins.bool"}}}, "tuple_type": null, "type_vars": [], "typeddict_type": null}}, "_decompose_class": {".class": "SymbolTableNode", "kind": "Mdef", "node": {".class": "Decorator", "func": {".class": "FuncDef", "arg_kinds": [0, 0], "arg_names": ["cls", "obj"], "flags": ["is_class", "is_decorated"], "fullname": "ninja.schema.Schema._decompose_class", "name": "_decompose_class", "type": {".class": "CallableType", "arg_kinds": [0, 0], "arg_names": ["cls", "obj"], "arg_types": [{".class": "TypeType", "item": "ninja.schema.Schema"}, {".class": "AnyType", "missing_import_name": null, "source_any": null, "type_of_any": 2}], "bound_args": [], "def_extras": {"first_arg": "cls"}, "fallback": "builtins.function", "implicit": false, "is_ellipsis_args": false, "name": "_decompose_class of Schema", "ret_type": "pydantic.utils.GetterDict", "variables": []}}, "is_overload": false, "var": {".class": "Var", "flags": ["is_initialized_in_class", "is_classmethod", "is_ready"], "fullname": null, "name": "_decompose_class", "type": {".class": "CallableType", "arg_kinds": [0, 0], "arg_names": ["cls", "obj"], "arg_types": [{".class": "TypeType", "item": "ninja.schema.Schema"}, {".class": "AnyType", "missing_import_name": null, "source_any": null, "type_of_any": 2}], "bound_args": [], "def_extras": {"first_arg": "cls"}, "fallback": "builtins.function", "implicit": false, "is_ellipsis_args": false, "name": "_decompose_class of Schema", "ret_type": "pydantic.utils.GetterDict", "variables": []}}}}, "from_orm": {".class": "SymbolTableNode", "kind": "Mdef", "node": {".class": "Decorator", "func": {".class": "FuncDef", "arg_kinds": [0, 0], "arg_names": ["cls", "obj"], "flags": ["is_class", "is_decorated"], "fullname": "ninja.schema.Schema.from_orm", "name": "from_orm", "type": {".class": "CallableType", "arg_kinds": [0, 0], "arg_names": ["cls", "obj"], "arg_types": [{".class": "TypeType", "item": {".class": "TypeVarType", "fullname": "ninja.schema.S", "id": -1, "name": "S", "upper_bound": "ninja.schema.Schema", "values": [], "variance": 0}}, {".class": "AnyType", "missing_import_name": null, "source_any": null, "type_of_any": 2}], "bound_args": [], "def_extras": {"first_arg": "cls"}, "fallback": "builtins.function", "implicit": false, "is_ellipsis_args": false, "name": "from_orm of Schema", "ret_type": {".class": "TypeVarType", "fullname": "ninja.schema.S", "id": -1, "name": "S", "upper_bound": "ninja.schema.Schema", "values": [], "variance": 0}, "variables": [{".class": "TypeVarDef", "fullname": "ninja.schema.S", "id": -1, "name": "S", "upper_bound": "ninja.schema.Schema", "values": [], "variance": 0}]}}, "is_overload": false, "var": {".class": "Var", "flags": ["is_initialized_in_class", "is_classmethod", "is_ready"], "fullname": null, "name": "from_orm", "type": {".class": "CallableType", "arg_kinds": [0, 0], "arg_names": ["cls", "obj"], "arg_types": [{".class": "TypeType", "item": {".class": "TypeVarType", "fullname": "ninja.schema.S", "id": -1, "name": "S", "upper_bound": "ninja.schema.Schema", "values": [], "variance": 0}}, {".class": "AnyType", "missing_import_name": null, "source_any": null, "type_of_any": 2}], "bound_args": [], "def_extras": {"first_arg": "cls"}, "fallback": "builtins.function", "implicit": false, "is_ellipsis_args": false, "name": "from_orm of Schema", "ret_type": {".class": "TypeVarType", "fullname": "ninja.schema.S", "id": -1, "name": "S", "upper_bound": "ninja.schema.Schema", "values": [], "variance": 0}, "variables": [{".class": "TypeVarDef", "fullname": "ninja.schema.S", "id": -1, "name": "S", "upper_bound": "ninja.schema.Schema", "values": [], "variance": 0}]}}}}}, "tuple_type": null, "type_vars": [], "typeddict_type": null}}, "Type": {".class": "SymbolTableNode", "cross_ref": "typing.Type", "kind": "Gdef", "module_public": false}, "TypeVar": {".class": "SymbolTableNode", "cross_ref": "typing.TypeVar", "kind": "Gdef", "module_public": false}, "Union": {".class": "SymbolTableNode", "cross_ref": "typing.Union", "kind": "Gdef", "module_public": false}, "Variable": {".class": "SymbolTableNode", "kind": "Gdef", "module_public": false, "node": {".class": "Var", "flags": ["is_suppressed_import", "is_ready"], "fullname": "ninja.schema.Variable", "name": "Variable", "type": {".class": "AnyType", "missing_import_name": "ninja.schema.Variable", "source_any": null, "type_of_any": 3}}}, "VariableDoesNotExist": {".class": "SymbolTableNode", "kind": "Gdef", "module_public": false, "node": {".class": "Var", "flags": ["is_suppressed_import", "is_ready"], "fullname": "ninja.schema.VariableDoesNotExist", "name": "VariableDoesNotExist", "type": {".class": "AnyType", "missing_import_name": "ninja.schema.VariableDoesNotExist", "source_any": null, "type_of_any": 3}}}, "__all__": {".class": "SymbolTableNode", "kind": "Gdef", "module_public": false, "node": {".class": "Var", "flags": [], "fullname": "ninja.schema.__all__", "name": "__all__", "type": {".class": "Instance", "args": ["builtins.str"], "type_ref": "builtins.list"}}}, "__doc__": {".class": "SymbolTableNode", "kind": "Gdef", "module_public": false, "node": {".class": "Var", "flags": ["is_ready"], "fullname": "ninja.schema.__doc__", "name": "__doc__", "type": "builtins.str"}}, "__file__": {".class": "SymbolTableNode", "kind": "Gdef", "module_public": false, "node": {".class": "Var", "flags": ["is_ready"], "fullname": "ninja.schema.__file__", "name": "__file__", "type": "builtins.str"}}, "__name__": {".class": "SymbolTableNode", "kind": "Gdef", "module_public": false, "node": {".class": "Var", "flags": ["is_ready"], "fullname": "ninja.schema.__name__", "name": "__name__", "type": "builtins.str"}}, "__package__": {".class": "SymbolTableNode", "kind": "Gdef", "module_public": false, "node": {".class": "Var", "flags": ["is_ready"], "fullname": "ninja.schema.__package__", "name": "__package__", "type": "builtins.str"}}, "no_type_check": {".class": "SymbolTableNode", "cross_ref": "typing.no_type_check", "kind": "Gdef", "module_public": false}, "pydantic": {".class": "SymbolTableNode", "cross_ref": "pydantic", "kind": "Gdef", "module_public": false}, "pydantic_version": {".class": "SymbolTableNode", "kind": "Gdef", "module_public": false, "node": {".class": "Var", "flags": [], "fullname": "ninja.schema.pydantic_version", "name": "pydantic_version", "type": {".class": "Instance", "args": ["builtins.int"], "type_ref": "builtins.list"}}}, "validator": {".class": "SymbolTableNode", "cross_ref": "pydantic.class_validators.validator", "kind": "Gdef"}}, "path": "/home/gatepass/.local/lib/python3.8/site-packages/ninja/schema.py"}