{".class": "MypyFile", "_fullname": "ninja.orm.factory", "is_partial_stub_package": false, "is_stub": false, "names": {".class": "SymbolTable", "Any": {".class": "SymbolTableNode", "cross_ref": "typing.Any", "kind": "Gdef", "module_public": false}, "ConfigError": {".class": "SymbolTableNode", "cross_ref": "ninja.errors.ConfigError", "kind": "Gdef", "module_public": false}, "Dict": {".class": "SymbolTableNode", "cross_ref": "typing.Dict", "kind": "Gdef", "module_public": false}, "Field": {".class": "SymbolTableNode", "kind": "Gdef", "module_public": false, "node": {".class": "Var", "flags": ["is_suppressed_import", "is_ready"], "fullname": "ninja.orm.factory.Field", "name": "Field", "type": {".class": "AnyType", "missing_import_name": "ninja.orm.factory.Field", "source_any": null, "type_of_any": 3}}}, "Iterator": {".class": "SymbolTableNode", "cross_ref": "typing.Iterator", "kind": "Gdef", "module_public": false}, "List": {".class": "SymbolTableNode", "cross_ref": "typing.List", "kind": "Gdef", "module_public": false}, "ManyToManyRel": {".class": "SymbolTableNode", "kind": "Gdef", "module_public": false, "node": {".class": "Var", "flags": ["is_suppressed_import", "is_ready"], "fullname": "ninja.orm.factory.ManyToManyRel", "name": "ManyToManyRel", "type": {".class": "AnyType", "missing_import_name": "ninja.orm.factory.ManyToManyRel", "source_any": null, "type_of_any": 3}}}, "ManyToOneRel": {".class": "SymbolTableNode", "kind": "Gdef", "module_public": false, "node": {".class": "Var", "flags": ["is_suppressed_import", "is_ready"], "fullname": "ninja.orm.factory.ManyToOneRel", "name": "ManyToOneRel", "type": {".class": "AnyType", "missing_import_name": "ninja.orm.factory.ManyToOneRel", "source_any": null, "type_of_any": 3}}}, "Model": {".class": "SymbolTableNode", "kind": "Gdef", "module_public": false, "node": {".class": "Var", "flags": ["is_suppressed_import", "is_ready"], "fullname": "ninja.orm.factory.Model", "name": "Model", "type": {".class": "AnyType", "missing_import_name": "ninja.orm.factory.Model", "source_any": null, "type_of_any": 3}}}, "Optional": {".class": "SymbolTableNode", "cross_ref": "typing.Optional", "kind": "Gdef", "module_public": false}, "Schema": {".class": "SymbolTableNode", "cross_ref": "ninja.schema.Schema", "kind": "Gdef", "module_public": false}, "SchemaFactory": {".class": "SymbolTableNode", "kind": "Gdef", "node": {".class": "TypeInfo", "_promote": null, "abstract_attributes": [], "bases": ["builtins.object"], "declared_metaclass": null, "defn": {".class": "ClassDef", "fullname": "ninja.orm.factory.SchemaFactory", "name": "SchemaFactory", "type_vars": []}, "flags": [], "fullname": "ninja.orm.factory.SchemaFactory", "metaclass_type": null, "metadata": {}, "module_name": "ninja.orm.factory", "mro": ["ninja.orm.factory.SchemaFactory", "builtins.object"], "names": {".class": "SymbolTable", "__init__": {".class": "SymbolTableNode", "kind": "Mdef", "node": {".class": "FuncDef", "arg_kinds": [0], "arg_names": ["self"], "flags": [], "fullname": "ninja.orm.factory.SchemaFactory.__init__", "name": "__init__", "type": {".class": "CallableType", "arg_kinds": [0], "arg_names": ["self"], "arg_types": ["ninja.orm.factory.SchemaFactory"], "bound_args": [], "def_extras": {"first_arg": "self"}, "fallback": "builtins.function", "implicit": false, "is_ellipsis_args": false, "name": "__init__ of SchemaFactory", "ret_type": {".class": "NoneType"}, "variables": []}}}, "_get_unique_name": {".class": "SymbolTableNode", "kind": "Mdef", "node": {".class": "FuncDef", "arg_kinds": [0, 0], "arg_names": ["self", "name"], "flags": [], "fullname": "ninja.orm.factory.SchemaFactory._get_unique_name", "name": "_get_unique_name", "type": {".class": "CallableType", "arg_kinds": [0, 0], "arg_names": ["self", "name"], "arg_types": ["ninja.orm.factory.SchemaFactory", "builtins.str"], "bound_args": [], "def_extras": {"first_arg": "self"}, "fallback": "builtins.function", "implicit": false, "is_ellipsis_args": false, "name": "_get_unique_name of SchemaFactory", "ret_type": "builtins.str", "variables": []}}}, "_model_fields": {".class": "SymbolTableNode", "kind": "Mdef", "node": {".class": "FuncDef", "arg_kinds": [0, 0], "arg_names": ["self", "model"], "flags": ["is_generator"], "fullname": "ninja.orm.factory.SchemaFactory._model_fields", "name": "_model_fields", "type": {".class": "CallableType", "arg_kinds": [0, 0], "arg_names": ["self", "model"], "arg_types": ["ninja.orm.factory.SchemaFactory", {".class": "TypeType", "item": {".class": "AnyType", "missing_import_name": "ninja.orm.factory.Model", "source_any": null, "type_of_any": 3}}], "bound_args": [], "def_extras": {"first_arg": "self"}, "fallback": "builtins.function", "implicit": false, "is_ellipsis_args": false, "name": "_model_fields of SchemaFactory", "ret_type": {".class": "Instance", "args": [{".class": "AnyType", "missing_import_name": "ninja.orm.factory.Field", "source_any": null, "type_of_any": 3}], "type_ref": "typing.Iterator"}, "variables": []}}}, "_selected_model_fields": {".class": "SymbolTableNode", "kind": "Mdef", "node": {".class": "FuncDef", "arg_kinds": [0, 0, 1, 1], "arg_names": ["self", "model", "fields", "exclude"], "flags": ["is_generator"], "fullname": "ninja.orm.factory.SchemaFactory._selected_model_fields", "name": "_selected_model_fields", "type": {".class": "CallableType", "arg_kinds": [0, 0, 1, 1], "arg_names": ["self", "model", "fields", "exclude"], "arg_types": ["ninja.orm.factory.SchemaFactory", {".class": "TypeType", "item": {".class": "AnyType", "missing_import_name": "ninja.orm.factory.Model", "source_any": null, "type_of_any": 3}}, {".class": "UnionType", "items": [{".class": "Instance", "args": ["builtins.str"], "type_ref": "builtins.list"}, {".class": "NoneType"}]}, {".class": "UnionType", "items": [{".class": "Instance", "args": ["builtins.str"], "type_ref": "builtins.list"}, {".class": "NoneType"}]}], "bound_args": [], "def_extras": {"first_arg": "self"}, "fallback": "builtins.function", "implicit": false, "is_ellipsis_args": false, "name": "_selected_model_fields of SchemaFactory", "ret_type": {".class": "Instance", "args": [{".class": "AnyType", "missing_import_name": "ninja.orm.factory.Field", "source_any": null, "type_of_any": 3}], "type_ref": "typing.Iterator"}, "variables": []}}}, "create_schema": {".class": "SymbolTableNode", "kind": "Mdef", "node": {".class": "FuncDef", "arg_kinds": [0, 0, 5, 5, 5, 5, 5, 5, 5], "arg_names": ["self", "model", "name", "depth", "fields", "exclude", "optional_fields", "custom_fields", "base_class"], "flags": [], "fullname": "ninja.orm.factory.SchemaFactory.create_schema", "name": "create_schema", "type": {".class": "CallableType", "arg_kinds": [0, 0, 5, 5, 5, 5, 5, 5, 5], "arg_names": ["self", "model", "name", "depth", "fields", "exclude", "optional_fields", "custom_fields", "base_class"], "arg_types": ["ninja.orm.factory.SchemaFactory", {".class": "TypeType", "item": {".class": "AnyType", "missing_import_name": "ninja.orm.factory.Model", "source_any": null, "type_of_any": 3}}, "builtins.str", "builtins.int", {".class": "UnionType", "items": [{".class": "Instance", "args": ["builtins.str"], "type_ref": "builtins.list"}, {".class": "NoneType"}]}, {".class": "UnionType", "items": [{".class": "Instance", "args": ["builtins.str"], "type_ref": "builtins.list"}, {".class": "NoneType"}]}, {".class": "UnionType", "items": [{".class": "Instance", "args": ["builtins.str"], "type_ref": "builtins.list"}, {".class": "NoneType"}]}, {".class": "UnionType", "items": [{".class": "Instance", "args": [{".class": "TupleType", "implicit": false, "items": ["builtins.str", {".class": "AnyType", "missing_import_name": null, "source_any": null, "type_of_any": 2}, {".class": "AnyType", "missing_import_name": null, "source_any": null, "type_of_any": 2}], "partial_fallback": {".class": "Instance", "args": [{".class": "AnyType", "missing_import_name": null, "source_any": null, "type_of_any": 6}], "type_ref": "builtins.tuple"}}], "type_ref": "builtins.list"}, {".class": "NoneType"}]}, {".class": "TypeType", "item": "ninja.schema.Schema"}], "bound_args": [], "def_extras": {"first_arg": "self"}, "fallback": "builtins.function", "implicit": false, "is_ellipsis_args": false, "name": "create_schema of SchemaFactory", "ret_type": {".class": "TypeType", "item": "ninja.schema.Schema"}, "variables": []}}}, "get_key": {".class": "SymbolTableNode", "kind": "Mdef", "node": {".class": "FuncDef", "arg_kinds": [0, 0, 0, 0, 0, 0, 0, 0], "arg_names": ["self", "model", "name", "depth", "fields", "exclude", "optional_fields", "custom_fields"], "flags": [], "fullname": "ninja.orm.factory.SchemaFactory.get_key", "name": "get_key", "type": {".class": "CallableType", "arg_kinds": [0, 0, 0, 0, 0, 0, 0, 0], "arg_names": ["self", "model", "name", "depth", "fields", "exclude", "optional_fields", "custom_fields"], "arg_types": ["ninja.orm.factory.SchemaFactory", {".class": "TypeType", "item": {".class": "AnyType", "missing_import_name": "ninja.orm.factory.Model", "source_any": null, "type_of_any": 3}}, "builtins.str", "builtins.int", {".class": "UnionType", "items": ["builtins.str", {".class": "Instance", "args": ["builtins.str"], "type_ref": "builtins.list"}, {".class": "NoneType"}]}, {".class": "UnionType", "items": [{".class": "Instance", "args": ["builtins.str"], "type_ref": "builtins.list"}, {".class": "NoneType"}]}, {".class": "UnionType", "items": [{".class": "Instance", "args": ["builtins.str"], "type_ref": "builtins.list"}, "builtins.str", {".class": "NoneType"}]}, {".class": "UnionType", "items": [{".class": "Instance", "args": [{".class": "TupleType", "implicit": false, "items": ["builtins.str", "builtins.str", {".class": "AnyType", "missing_import_name": null, "source_any": null, "type_of_any": 2}], "partial_fallback": {".class": "Instance", "args": [{".class": "AnyType", "missing_import_name": null, "source_any": null, "type_of_any": 6}], "type_ref": "builtins.tuple"}}], "type_ref": "builtins.list"}, {".class": "NoneType"}]}], "bound_args": [], "def_extras": {"first_arg": "self"}, "fallback": "builtins.function", "implicit": false, "is_ellipsis_args": false, "name": "get_key of SchemaFactory", "ret_type": {".class": "TypeAliasType", "args": [], "type_ref": "ninja.orm.factory.SchemaKey"}, "variables": []}}}, "schema_names": {".class": "SymbolTableNode", "implicit": true, "kind": "Mdef", "node": {".class": "Var", "flags": ["explicit_self_type", "is_ready"], "fullname": "ninja.orm.factory.SchemaFactory.schema_names", "name": "schema_names", "type": {".class": "Instance", "args": ["builtins.str"], "type_ref": "builtins.set"}}}, "schemas": {".class": "SymbolTableNode", "implicit": true, "kind": "Mdef", "node": {".class": "Var", "flags": ["explicit_self_type", "is_ready"], "fullname": "ninja.orm.factory.SchemaFactory.schemas", "name": "schemas", "type": {".class": "Instance", "args": [{".class": "TypeAliasType", "args": [], "type_ref": "ninja.orm.factory.SchemaKey"}, {".class": "TypeType", "item": "ninja.schema.Schema"}], "type_ref": "builtins.dict"}}}}, "tuple_type": null, "type_vars": [], "typeddict_type": null}}, "SchemaKey": {".class": "SymbolTableNode", "kind": "Gdef", "module_public": false, "node": {".class": "TypeAlias", "alias_tvars": [], "column": 0, "fullname": "ninja.orm.factory.SchemaKey", "line": 26, "no_args": false, "normalized": false, "target": {".class": "TupleType", "implicit": false, "items": [{".class": "TypeType", "item": {".class": "AnyType", "missing_import_name": "ninja.orm.factory.Model", "source_any": null, "type_of_any": 3}}, "builtins.str", "builtins.int", "builtins.str", "builtins.str", "builtins.str", "builtins.str"], "partial_fallback": {".class": "Instance", "args": [{".class": "AnyType", "missing_import_name": null, "source_any": null, "type_of_any": 6}], "type_ref": "builtins.tuple"}}}}, "Set": {".class": "SymbolTableNode", "cross_ref": "typing.Set", "kind": "Gdef", "module_public": false}, "Tuple": {".class": "SymbolTableNode", "cross_ref": "typing.Tuple", "kind": "Gdef", "module_public": false}, "Type": {".class": "SymbolTableNode", "cross_ref": "typing.Type", "kind": "Gdef", "module_public": false}, "Union": {".class": "SymbolTableNode", "cross_ref": "typing.Union", "kind": "Gdef", "module_public": false}, "__all__": {".class": "SymbolTableNode", "kind": "Gdef", "module_public": false, "node": {".class": "Var", "flags": [], "fullname": "ninja.orm.factory.__all__", "name": "__all__", "type": {".class": "Instance", "args": ["builtins.str"], "type_ref": "builtins.list"}}}, "__doc__": {".class": "SymbolTableNode", "kind": "Gdef", "module_public": false, "node": {".class": "Var", "flags": ["is_ready"], "fullname": "ninja.orm.factory.__doc__", "name": "__doc__", "type": "builtins.str"}}, "__file__": {".class": "SymbolTableNode", "kind": "Gdef", "module_public": false, "node": {".class": "Var", "flags": ["is_ready"], "fullname": "ninja.orm.factory.__file__", "name": "__file__", "type": "builtins.str"}}, "__name__": {".class": "SymbolTableNode", "kind": "Gdef", "module_public": false, "node": {".class": "Var", "flags": ["is_ready"], "fullname": "ninja.orm.factory.__name__", "name": "__name__", "type": "builtins.str"}}, "__package__": {".class": "SymbolTableNode", "kind": "Gdef", "module_public": false, "node": {".class": "Var", "flags": ["is_ready"], "fullname": "ninja.orm.factory.__package__", "name": "__package__", "type": "builtins.str"}}, "cast": {".class": "SymbolTableNode", "cross_ref": "typing.cast", "kind": "Gdef", "module_public": false}, "create_pydantic_model": {".class": "SymbolTableNode", "cross_ref": "pydantic.main.create_model", "kind": "Gdef", "module_public": false}, "create_schema": {".class": "SymbolTableNode", "kind": "Gdef", "node": {".class": "Var", "flags": [], "fullname": "ninja.orm.factory.create_schema", "name": "create_schema", "type": {".class": "CallableType", "arg_kinds": [0, 5, 5, 5, 5, 5, 5, 5], "arg_names": ["model", "name", "depth", "fields", "exclude", "optional_fields", "custom_fields", "base_class"], "arg_types": [{".class": "TypeType", "item": {".class": "AnyType", "missing_import_name": "ninja.orm.factory.Model", "source_any": null, "type_of_any": 3}}, "builtins.str", "builtins.int", {".class": "UnionType", "items": [{".class": "Instance", "args": ["builtins.str"], "type_ref": "builtins.list"}, {".class": "NoneType"}]}, {".class": "UnionType", "items": [{".class": "Instance", "args": ["builtins.str"], "type_ref": "builtins.list"}, {".class": "NoneType"}]}, {".class": "UnionType", "items": [{".class": "Instance", "args": ["builtins.str"], "type_ref": "builtins.list"}, {".class": "NoneType"}]}, {".class": "UnionType", "items": [{".class": "Instance", "args": [{".class": "TupleType", "implicit": false, "items": ["builtins.str", {".class": "AnyType", "missing_import_name": null, "source_any": null, "type_of_any": 2}, {".class": "AnyType", "missing_import_name": null, "source_any": null, "type_of_any": 2}], "partial_fallback": {".class": "Instance", "args": [{".class": "AnyType", "missing_import_name": null, "source_any": null, "type_of_any": 6}], "type_ref": "builtins.tuple"}}], "type_ref": "builtins.list"}, {".class": "NoneType"}]}, {".class": "TypeType", "item": "ninja.schema.Schema"}], "bound_args": ["ninja.orm.factory.SchemaFactory"], "def_extras": {"first_arg": "self"}, "fallback": "builtins.function", "implicit": false, "is_ellipsis_args": false, "name": null, "ret_type": {".class": "TypeType", "item": "ninja.schema.Schema"}, "variables": []}}}, "factory": {".class": "SymbolTableNode", "kind": "Gdef", "node": {".class": "Var", "flags": [], "fullname": "ninja.orm.factory.factory", "name": "factory", "type": "ninja.orm.factory.SchemaFactory"}}, "get_schema_field": {".class": "SymbolTableNode", "cross_ref": "ninja.orm.fields.get_schema_field", "kind": "Gdef", "module_public": false}, "itertools": {".class": "SymbolTableNode", "cross_ref": "itertools", "kind": "Gdef", "module_public": false}}, "path": "/home/gatepass/.local/lib/python3.8/site-packages/ninja/orm/factory.py"}